{
  "lastUpdated": "2026-05-07T22:29:03.192Z",
  "data": {
    "IBIT": {
      "symbol": "IBIT",
      "error": "HTTP 401",
      "fetchedAt": "2026-05-07T22:28:56.899Z"
    },
    "ETHA": {
      "symbol": "ETHA",
      "error": "HTTP 401",
      "fetchedAt": "2026-05-07T22:28:57.947Z"
    },
    "FBTC": {
      "symbol": "FBTC",
      "error": "HTTP 401",
      "fetchedAt": "2026-05-07T22:28:59.024Z"
    },
    "ARKB": {
      "symbol": "ARKB",
      "error": "HTTP 401",
      "fetchedAt": "2026-05-07T22:29:00.103Z"
    },
    "BITB": {
      "symbol": "BITB",
      "error": "HTTP 401",
      "fetchedAt": "2026-05-07T22:29:01.147Z"
    },
    "GBTC": {
      "symbol": "GBTC",
      "error": "HTTP 401",
      "fetchedAt": "2026-05-07T22:29:02.191Z"
    }
  }
}